myPackageTFIMM/DLA34.py
myPackageTFIMM/DPN92.py
myPackageTFIMM/InceptionV3.py
myPackageTFIMM/ResNeXt.py
myPackageTFIMM/VisionTransformer.py
myPackageTFIMM/Xception.py
myPackageTFIMM/__init__.py
myPackageTFIMM/all_models.py
myPackageTFIMM/efficient_net_b0.py
myPackageTFIMM/importLayers.py
myPackageTFIMM/main.py
myPackageTFIMM-0.0.4.dist-info/METADATA
myPackageTFIMM-0.0.4.dist-info/WHEEL
myPackageTFIMM-0.0.4.dist-info/license.txt
myPackageTFIMM-0.0.4.dist-info/top_level.txt
myPackageTFIMM-0.0.4.dist-info/RECORD
