Metadata-Version: 2.1
Name: myPackageTFIMM
Version: 0.0.4
Summary: image models
Author: Alaa Elmor
Author-email: alaa.m.elmor@gmail.com
Classifier: Programming Language :: Python :: 3
Classifier: License :: OSI Approved :: MIT License
Classifier: Operating System :: OS Independent
Requires-Python: >=3.6
License-File: license.txt
